articles/__init__.py
articles/extractors.py
articles/html.py
articles/mss/__init__.py
articles/mss/extractors.py
articles/mss/scores.py
article_extraction-0.3.0.dist-info/LICENSE
article_extraction-0.3.0.dist-info/WHEEL
article_extraction-0.3.0.dist-info/METADATA
article_extraction-0.3.0.dist-info/RECORD
